README.md
setup.py
mls/__init__.py
mls/__main__.py
mls/mls.py
movielinkscraper.egg-info/PKG-INFO
movielinkscraper.egg-info/SOURCES.txt
movielinkscraper.egg-info/dependency_links.txt
movielinkscraper.egg-info/requires.txt
movielinkscraper.egg-info/top_level.txt